AUTHORS.md
HISTORY.md
README.md
fast/__init__.py
fast/cbfs.py
fast/density.py
fast/fast.py
fast/find_ast_visitor.py
fast/multi_grep.py
fast/objective_func.py
fast/pattern_automaton.py
fast/random.py
fast/regexp.py
fast/regexp_ast.py
fast/regexp_mutators.py
find_abstract_syntax_tree-0.2.1.dist-info/METADATA
find_abstract_syntax_tree-0.2.1.dist-info/LICENSE
find_abstract_syntax_tree-0.2.1.dist-info/WHEEL
find_abstract_syntax_tree-0.2.1.dist-info/RECORD
