Metadata-Version: 2.1
Name: find-abstract-syntax-tree
Version: 0.2.1
Summary: Python3 module inferring Abstract Syntax Trees (AST) representing regular expressions (RE) given a set of positive examples.
License: BSD-3 license
Author: Maxime Raynal
Author-email: maxime.raynal@nokia.com
Requires-Python: >=3.8,<4.0
Classifier: License :: Other/Proprietary License
Classifier: Programming Language :: Python :: 3
Classifier: Programming Language :: Python :: 3.8
Classifier: Programming Language :: Python :: 3.9
Classifier: Programming Language :: Python :: 3.10
Classifier: Programming Language :: Python :: 3.11
Requires-Dist: pybgl (>=0.11.2)
